{
  "museum": {
    "name": "Elysian Art and History Museum",
    "location": {
      "city": "Athens",
      "country": "Greece"
    },
    "established_year": 1923,
    "director": {
      "full_name": "Dr. Sophia Demetriou",
      "tenure_years": 8
    },
    "collections": [
      {
        "title": "Ancient Greek Sculptures",
        "category": "Sculpture",
        "items_count": 1200,
        "curator": "Mr. Nikos Papadopoulos",
        "highlighted_items": [
          {
            "name": "The Discus Thrower",
            "origin": "Ancient Greece",
            "year": 450,
            "description": "A renowned statue depicting the idealized athletic form of ancient Greek athletes."
          }
        ]
      },
      {
        "title": "Modern European Paintings",
        "category": "Painting",
        "items_count": 850,
        "curator": "Ms. Elena Rossi",
        "highlighted_items": [
          {
            "name": "Sunlit Boulevard",
            "origin": "France",
            "year": "1925",
            "description": "A vibrant depiction of Parisian street life by the impressionist painter Camille Dubois."
          }
        ]
      },
      {
        "title": "Maritime History",
        "category": "Historical Artifacts",
        "items_count": 500,
        "curator": "Captain Andreas Marineos",
        "highlighted_items": [
          {
            "name": "Athenian Trireme Model",
            "origin": "Ancient Athens",
            "year": 400,
            "description": "A detailed scale model of a trireme, showcasing the naval prowess of ancient Athenian society."
          }
        ]
      }
    ],
    "visitor_statistics": {
      "annual_visitors": 350000,
      "last_updated": "2023-04-15"
    }
  }
}