
<planet>
  <name>Gliese 581g</name>
  <system>
    <star>
      <name>Gliese 581</name>
      <type>Red Dwarf</type>
      <distance_from_earth_ly>20.3</distance_from_earth_ly>
    </star>
  </system>
  <moons>
    <moon>
      <name>Phobos</name>
      <diameter_km>22.2</diameter_km>
      <has_atmosphere>False</has_atmosphere>
    </moon>
    <moon>
      <name>Deimos</name>
      <diameter_km>12.4</diameter_km>
      <has_atmosphere>False</has_atmosphere>
    </moon>
  </moons>
  <exploration_missions>
    <mission>
      <name>Project Pioneer</name>
      <launch_year>2041</launch_year>
      <crew_members>
        <crew_member>
          <name>Dr. Ada Lovelace</name>
          <role>Commander</role>
        </crew_member>
        <crew_member>
          <name>Elon Tusk</name>
          <role>Pilot</role>
        </crew_member>
      </crew_members>
    </mission>
  </exploration_missions>
</planet>
