
{
    "name": "Xeridia",
    "type": "Reptilian",
    "origin": {
        "planet": "Xeridia-IV",
        "galaxy": "Andromeda"
    },
    "abilities": [
        {
            "name": "Energy Projection",
            "power_level": 8
        },
        {
            "name": "Camouflage",
            "power_level": 5
        }
    ],
    "habitat": {
        "environment": "Desert",
        "temperature_range": "-20C to 40C",
        "resources": [
            "Water",
            "Minerals"
        ]
    },
    "appearance": {
        "color": "Brown",
        "size": "1.5 meters",
        "distinctive_feature": "Spines"
    }
}
