[
    {
        "astronaut_id": "A-102",
        "name.first": "Valentina",
        "name.last": "Tereshkova",
        "missions[0].mission_name": "Vostok 6",
        "missions[0].year": "1963",
        "missions[0].duration_days": "3",
        "missions[0].crew_members": "Valentina Tereshkova;Sergei Korolev",
        "missions[1].mission_name": "Soyuz 13",
        "missions[1].year": "1973",
        "missions[1].duration_days": "8",
        "missions[1].crew_members": "Pyotr Klimuk;Valentina Tereshkova",
        "training.completed": true,
        "training.specializations[0]": "Astrophysics",
        "training.specializations[1]": "Parachuting",
        "equipment.helmet.serial_number": "H-001",
        "equipment.helmet.last_inspection": "2023-08-12",
        "equipment.suit.serial_number": "S-003",
        "equipment.suit.last_inspection": "2024-01-15",
        "awards[0].title": "Hero of the Soviet Union",
        "awards[0].year": "1963",
        "awards[1].title": "Order of Lenin",
        "awards[1].year": "1963"
    },
    {
        "astronaut_id": "A-207",
        "name.first": "Chris",
        "name.last": "Hadfield",
        "missions[0].mission_name": "STS-74",
        "missions[0].year": "1995",
        "missions[0].duration_days": "8",
        "missions[0].crew_members": "Chris Hadfield;Ken Cameron",
        "missions[1].mission_name": "Expedition 35",
        "missions[1].year": "2013",
        "missions[1].duration_days": "146",
        "missions[1].crew_members": "Chris Hadfield;Tom Marshburn",
        "training.completed": true,
        "training.specializations[0]": "Engineering",
        "training.specializations[1]": "Music",
        "equipment.helmet.serial_number": "H-045",
        "equipment.helmet.last_inspection": "2022-07-10",
        "equipment.suit.serial_number": "S-021",
        "equipment.suit.last_inspection": "2023-12-05",
        "awards[0].title": "Order of Canada",
        "awards[0].year": "2014",
        "awards[1].title": "Canadian Space Medal",
        "awards[1].year": "2013"
    }
]