
{
  "artifact": {
    "name": "Celestial Disc of Ur",
    "origin": {
      "civilization": "Sumerian",
      "era": "Third Millennium BCE"
    },
    "materials": [
      {
        "type": "Copper",
        "provenance": "Local mines near Ur"
      },
      {
        "type": "Lapis Lazuli",
        "provenance": "Mountains of Afghanistan"
      }
    ],
    "dimensions": {
      "height_cm": 12.5,
      "width_cm": 10.2,
      "depth_cm": 3.8
    },
    "inscriptions": [
      {
        "language": "Sumerian cuneiform",
        "translation": "The heavens are in order, the earth is stable.",
        "position": "Central circular band"
      },
      {
        "language": "Akkadian cuneiform",
        "translation": "The gods watch over the city of Ur.",
        "position": "Peripheral rim"
      }
    ],
    "current_location": {
      "museum": "British Museum",
      "display_case": "Mesopotamian Antiquities Gallery"
    },
    "discovery": {
      "date": "1922-11-04",
      "discoverer": "Flinders Petrie"
    }
  }
}
