
<planet>
  <name>Virellion</name>
  <mass>6.8e24</mass>
  <orbit>
    <distance>1.2</distance>
    <period>450</period>
  </orbit>
  <atmosphere>
    <composition>Nitrogen, Oxygen, Argon, Carbon Dioxide</composition>
    <pressure>75.0</pressure>
  </atmosphere>
  <moons>
    <moon>
      <name>Lunara</name>
      <radius>1200</radius>
      <discovered_by>Dr. Elara Morn</discovered_by>
      <discovery_date>2085-03-15</discovery_date>
    </moon>
  </moons>
  <rings>
    <ring>
      <inner_radius>15000</inner_radius>
      <outer_radius>30000</outer_radius>
      <composition>Ice and Rock</composition>
    </ring>
  </rings>
</planet>
