
[
  {
    "species": "Rainbow Quokka",
    "habitat.type": "Forest",
    "habitat.location.latitude": -33.8679,
    "habitat.location.longitude": 151.2073,
    "diet.primary_foods": "leaves;berries;flowers",
    "diet.secondary_foods": "insects;fungi",
    "lifespan.average_years": 7,
    "lifespan.max_recorded": 12,
    "behaviors.migration_patterns": "seasonal;short-distance",
    "behaviors.social_structure": "matriarchal",
    "conservation_status.status": "Vulnerable",
    "conservation_status.population_estimate": 5000
  },
  {
    "species": "Azure Pangolin",
    "habitat.type": "Savannah",
    "habitat.location.latitude": 0.3476,
    "habitat.location.longitude": 32.5825,
    "diet.primary_foods": "ants;termites",
    "diet.secondary_foods": "fruits",
    "lifespan.average_years": 10,
    "lifespan.max_recorded": 18,
    "behaviors.migration_patterns": "nomadic;non-migratory",
    "behaviors.social_structure": "solitary",
    "conservation_status.status": "Endangered",
    "conservation_status.population_estimate": 1200
  }
]
